lib/tokenlib/__init__.py
lib/tokenlib/errors.py
lib/tokenlib/utils.py
lib/tokenlib/tests/__init__.py
lib/tokenlib/tests/test_tokens.py
lib/tokenlib/tests/test_utils.py
tokenlib/__init__.py
tokenlib/errors.py
tokenlib/utils.py
tokenlib/tests/__init__.py
tokenlib/tests/test_tokens.py
tokenlib/tests/test_utils.py
tokenlib-2.0.0.dist-info/DESCRIPTION.rst
tokenlib-2.0.0.dist-info/METADATA
tokenlib-2.0.0.dist-info/RECORD
tokenlib-2.0.0.dist-info/WHEEL
tokenlib-2.0.0.dist-info/metadata.json
tokenlib-2.0.0.dist-info/top_level.txt
