Metadata-Version: 2.0
Name: tokenlib
Version: 2.0.0
Summary: Generic library for managing signed authentication tokens.
Home-page: https://github.com/mozilla-services/tokenlib
Author: Mozilla Services
Author-email: services-dev@mozilla.org
License: MPLv2.0
Keywords: authentication token
Platform: UNKNOWN
Classifier: Intended Audience :: Developers
Classifier: Programming Language :: Python
Classifier: License :: OSI Approved :: Mozilla Public License 2.0 (MPL 2.0)
